usdanuts/__init__.py
usdanuts/usdanuts.py
usdanuts-0.0.5.dist-info/LICENSE.txt
usdanuts-0.0.5.dist-info/METADATA
usdanuts-0.0.5.dist-info/WHEEL
usdanuts-0.0.5.dist-info/top_level.txt
usdanuts-0.0.5.dist-info/RECORD
